Workbook

Sheet Resumo
A1: Resumo do negócio
A2: Tudo aqui é calculado a partir das outras abas. Não precisa digitar nada.
A4: Receita total | B4: =SUM(Vendas!G5:G504)
A5: Taxas dos canais | B5: =SUM(Vendas!H5:H504)
A6: Custo de produção das peças vendidas | B6: =SUM(Vendas!I5:I504)
A7: LUCRO DAS VENDAS | B7: =B4-B5-B6 | C7: Receita menos taxas e custo das peças
A8: Margem de lucro | B8: =IF(B4=0,0,B7/B4)
A9: Total gasto (compras e investimento) | B9: =SUM(Gastos!D5:D504)
A10: SALDO DE CAIXA | B10: =B4-B5-B9 | C10: Saldo negativo = ainda não recuperou o que investiu. Positivo = já se pagou.
A11: Peças vendidas | B11: =SUM(Vendas!C5:C504)
A13: Mês a mês
A14: Mês | B14: Receita | C14: Taxas | D14: Custo de produção | E14: Lucro das vendas | F14: Gastos | G14: Saldo do mês
A15: 46296 | B15: =SUMIFS(Vendas!$G$5:$G$504,Vendas!$A$5:$A$504,">="&$A15,Vendas!$A$5:$A$504,"<"&EDATE($A15,1)) | C15: =SUMIFS(Vendas!$H$5:$H$504,Vendas!$A$5:$A$504,">="&$A15,Vendas!$A$5:$A$504,"<"&EDATE($A15,1)) | D15: =SUMIFS(Vendas!$I$5:$I$504,Vendas!$A$5:$A$504,">="&$A15,Vendas!$A$5:$A$504,"<"&EDATE($A15,1)) | E15: =B15-C15-D15 | F15: =SUMIFS(Gastos!$D$5:$D$504,Gastos!$A$5:$A$504,">="&$A15,Gastos!$A$5:$A$504,"<"&EDATE($A15,1)) | G15: =B15-C15-F15
A16: =EDATE(A15,1) | B16: =SUMIFS(Vendas!$G$5:$G$504,Vendas!$A$5:$A$504,">="&$A16,Vendas!$A$5:$A$504,"<"&EDATE($A16,1)) | C16: =SUMIFS(Vendas!$H$5:$H$504,Vendas!$A$5:$A$504,">="&$A16,Vendas!$A$5:$A$504,"<"&EDATE($A16,1)) | D16: =SUMIFS(Vendas!$I$5:$I$504,Vendas!$A$5:$A$504,">="&$A16,Vendas!$A$5:$A$504,"<"&EDATE($A16,1)) | E16: =B16-C16-D16 | F16: =SUMIFS(Gastos!$D$5:$D$504,Gastos!$A$5:$A$504,">="&$A16,Gastos!$A$5:$A$504,"<"&EDATE($A16,1)) | G16: =B16-C16-F16
A17: =EDATE(A16,1) | B17: =SUMIFS(Vendas!$G$5:$G$504,Vendas!$A$5:$A$504,">="&$A17,Vendas!$A$5:$A$504,"<"&EDATE($A17,1)) | C17: =SUMIFS(Vendas!$H$5:$H$504,Vendas!$A$5:$A$504,">="&$A17,Vendas!$A$5:$A$504,"<"&EDATE($A17,1)) | D17: =SUMIFS(Vendas!$I$5:$I$504,Vendas!$A$5:$A$504,">="&$A17,Vendas!$A$5:$A$504,"<"&EDATE($A17,1)) | E17: =B17-C17-D17 | F17: =SUMIFS(Gastos!$D$5:$D$504,Gastos!$A$5:$A$504,">="&$A17,Gastos!$A$5:$A$504,"<"&EDATE($A17,1)) | G17: =B17-C17-F17
A18: =EDATE(A17,1) | B18: =SUMIFS(Vendas!$G$5:$G$504,Vendas!$A$5:$A$504,">="&$A18,Vendas!$A$5:$A$504,"<"&EDATE($A18,1)) | C18: =SUMIFS(Vendas!$H$5:$H$504,Vendas!$A$5:$A$504,">="&$A18,Vendas!$A$5:$A$504,"<"&EDATE($A18,1)) | D18: =SUMIFS(Vendas!$I$5:$I$504,Vendas!$A$5:$A$504,">="&$A18,Vendas!$A$5:$A$504,"<"&EDATE($A18,1)) | E18: =B18-C18-D18 | F18: =SUMIFS(Gastos!$D$5:$D$504,Gastos!$A$5:$A$504,">="&$A18,Gastos!$A$5:$A$504,"<"&EDATE($A18,1)) | G18: =B18-C18-F18
A19: =EDATE(A18,1) | B19: =SUMIFS(Vendas!$G$5:$G$504,Vendas!$A$5:$A$504,">="&$A19,Vendas!$A$5:$A$504,"<"&EDATE($A19,1)) | C19: =SUMIFS(Vendas!$H$5:$H$504,Vendas!$A$5:$A$504,">="&$A19,Vendas!$A$5:$A$504,"<"&EDATE($A19,1)) | D19: =SUMIFS(Vendas!$I$5:$I$504,Vendas!$A$5:$A$504,">="&$A19,Vendas!$A$5:$A$504,"<"&EDATE($A19,1)) | E19: =B19-C19-D19 | F19: =SUMIFS(Gastos!$D$5:$D$504,Gastos!$A$5:$A$504,">="&$A19,Gastos!$A$5:$A$504,"<"&EDATE($A19,1)) | G19: =B19-C19-F19
A20: =EDATE(A19,1) | B20: =SUMIFS(Vendas!$G$5:$G$504,Vendas!$A$5:$A$504,">="&$A20,Vendas!$A$5:$A$504,"<"&EDATE($A20,1)) | C20: =SUMIFS(Vendas!$H$5:$H$504,Vendas!$A$5:$A$504,">="&$A20,Vendas!$A$5:$A$504,"<"&EDATE($A20,1)) | D20: =SUMIFS(Vendas!$I$5:$I$504,Vendas!$A$5:$A$504,">="&$A20,Vendas!$A$5:$A$504,"<"&EDATE($A20,1)) | E20: =B20-C20-D20 | F20: =SUMIFS(Gastos!$D$5:$D$504,Gastos!$A$5:$A$504,">="&$A20,Gastos!$A$5:$A$504,"<"&EDATE($A20,1)) | G20: =B20-C20-F20
A21: =EDATE(A20,1) | B21: =SUMIFS(Vendas!$G$5:$G$504,Vendas!$A$5:$A$504,">="&$A21,Vendas!$A$5:$A$504,"<"&EDATE($A21,1)) | C21: =SUMIFS(Vendas!$H$5:$H$504,Vendas!$A$5:$A$504,">="&$A21,Vendas!$A$5:$A$504,"<"&EDATE($A21,1)) | D21: =SUMIFS(Vendas!$I$5:$I$504,Vendas!$A$5:$A$504,">="&$A21,Vendas!$A$5:$A$504,"<"&EDATE($A21,1)) | E21: =B21-C21-D21 | F21: =SUMIFS(Gastos!$D$5:$D$504,Gastos!$A$5:$A$504,">="&$A21,Gastos!$A$5:$A$504,"<"&EDATE($A21,1)) | G21: =B21-C21-F21
A22: =EDATE(A21,1) | B22: =SUMIFS(Vendas!$G$5:$G$504,Vendas!$A$5:$A$504,">="&$A22,Vendas!$A$5:$A$504,"<"&EDATE($A22,1)) | C22: =SUMIFS(Vendas!$H$5:$H$504,Vendas!$A$5:$A$504,">="&$A22,Vendas!$A$5:$A$504,"<"&EDATE($A22,1)) | D22: =SUMIFS(Vendas!$I$5:$I$504,Vendas!$A$5:$A$504,">="&$A22,Vendas!$A$5:$A$504,"<"&EDATE($A22,1)) | E22: =B22-C22-D22 | F22: =SUMIFS(Gastos!$D$5:$D$504,Gastos!$A$5:$A$504,">="&$A22,Gastos!$A$5:$A$504,"<"&EDATE($A22,1)) | G22: =B22-C22-F22
A23: =EDATE(A22,1) | B23: =SUMIFS(Vendas!$G$5:$G$504,Vendas!$A$5:$A$504,">="&$A23,Vendas!$A$5:$A$504,"<"&EDATE($A23,1)) | C23: =SUMIFS(Vendas!$H$5:$H$504,Vendas!$A$5:$A$504,">="&$A23,Vendas!$A$5:$A$504,"<"&EDATE($A23,1)) | D23: =SUMIFS(Vendas!$I$5:$I$504,Vendas!$A$5:$A$504,">="&$A23,Vendas!$A$5:$A$504,"<"&EDATE($A23,1)) | E23: =B23-C23-D23 | F23: =SUMIFS(Gastos!$D$5:$D$504,Gastos!$A$5:$A$504,">="&$A23,Gastos!$A$5:$A$504,"<"&EDATE($A23,1)) | G23: =B23-C23-F23
A24: =EDATE(A23,1) | B24: =SUMIFS(Vendas!$G$5:$G$504,Vendas!$A$5:$A$504,">="&$A24,Vendas!$A$5:$A$504,"<"&EDATE($A24,1)) | C24: =SUMIFS(Vendas!$H$5:$H$504,Vendas!$A$5:$A$504,">="&$A24,Vendas!$A$5:$A$504,"<"&EDATE($A24,1)) | D24: =SUMIFS(Vendas!$I$5:$I$504,Vendas!$A$5:$A$504,">="&$A24,Vendas!$A$5:$A$504,"<"&EDATE($A24,1)) | E24: =B24-C24-D24 | F24: =SUMIFS(Gastos!$D$5:$D$504,Gastos!$A$5:$A$504,">="&$A24,Gastos!$A$5:$A$504,"<"&EDATE($A24,1)) | G24: =B24-C24-F24
A25: =EDATE(A24,1) | B25: =SUMIFS(Vendas!$G$5:$G$504,Vendas!$A$5:$A$504,">="&$A25,Vendas!$A$5:$A$504,"<"&EDATE($A25,1)) | C25: =SUMIFS(Vendas!$H$5:$H$504,Vendas!$A$5:$A$504,">="&$A25,Vendas!$A$5:$A$504,"<"&EDATE($A25,1)) | D25: =SUMIFS(Vendas!$I$5:$I$504,Vendas!$A$5:$A$504,">="&$A25,Vendas!$A$5:$A$504,"<"&EDATE($A25,1)) | E25: =B25-C25-D25 | F25: =SUMIFS(Gastos!$D$5:$D$504,Gastos!$A$5:$A$504,">="&$A25,Gastos!$A$5:$A$504,"<"&EDATE($A25,1)) | G25: =B25-C25-F25
A26: =EDATE(A25,1) | B26: =SUMIFS(Vendas!$G$5:$G$504,Vendas!$A$5:$A$504,">="&$A26,Vendas!$A$5:$A$504,"<"&EDATE($A26,1)) | C26: =SUMIFS(Vendas!$H$5:$H$504,Vendas!$A$5:$A$504,">="&$A26,Vendas!$A$5:$A$504,"<"&EDATE($A26,1)) | D26: =SUMIFS(Vendas!$I$5:$I$504,Vendas!$A$5:$A$504,">="&$A26,Vendas!$A$5:$A$504,"<"&EDATE($A26,1)) | E26: =B26-C26-D26 | F26: =SUMIFS(Gastos!$D$5:$D$504,Gastos!$A$5:$A$504,">="&$A26,Gastos!$A$5:$A$504,"<"&EDATE($A26,1)) | G26: =B26-C26-F26
A28: Total | B28: =SUM(B15:B26) | C28: =SUM(C15:C26) | D28: =SUM(D15:D26) | E28: =SUM(E15:E26) | F28: =SUM(F15:F26) | G28: =SUM(G15:G26)
A30: Dica: o primeiro mês (amarelo) pode ser trocado; os outros seguem sozinhos.

Sheet Parâmetros
A1: Parâmetros
A2: Células amarelas com texto azul são para você editar. O resto calcula sozinho.
A4: Preço do filamento (R$ por kg) | B4: 100 | C4: Quanto você pagou no rolo de 1 kg. Confira na nota.
A5: Tarifa de energia (R$ por kWh) | B5: 0.9 | C5: Veja na sua conta de luz. Valor de exemplo.
A6: Consumo médio da impressora (kW) | B6: 0.1 | C6: A A1 gasta em média cerca de 0,1 kW imprimindo. Estimativa.
A7: Desgaste e manutenção (R$ por hora) | B7: 0.5 | C7: Bico, correia, falhas de impressão. Estimativa, ajuste com a experiência.
A8: Multiplicador do preço sugerido | B8: 3 | C8: Preço sugerido = custo x este valor. Use 3 a 4.
A9: Taxa padrão do canal de venda (%) | B9: 0.15 | C9: Mercado Livre/Shopee ~15-20%. Venda direta no WhatsApp = 0%.
A11: Como usar
A12: 1. Preencha os parâmetros acima.
A13: 2. Aba Produtos: cadastre cada peça (gramas e horas aparecem no Bambu Studio ao fatiar).
A14: 3. Aba Vendas: registre cada venda. O lucro é calculado sozinho.
A15: 4. Aba Gastos: registre tudo que você comprar (filamento, impressora, embalagem...).
A16: 5. Aba Resumo: veja lucro, margem e saldo de caixa.
A17: As linhas de exemplo estão em cinza claro no começo de cada aba. Apague-as e comece a sua.

Sheet Produtos
A1: Produtos e custo
A2: Cadastre as peças. Preencha só as colunas amarelas.
A4: Produto | B4: Gramas | C4: Horas de impressão | D4: Embalagem e extras (R$) | E4: Custo filamento | F4: Custo energia | G4: Desgaste | H4: CUSTO TOTAL | I4: Preço sugerido | J4: Preço que você cobra | K4: Lucro por unidade | L4: Margem | M4: Qtd vendida | N4: Lucro total
A5: Chaveiro com nome (EXEMPLO) | B5: 15 | C5: 1 | D5: 1 | E5: =IF(A5="","",B5/1000*Parâmetros!$B$4) | F5: =IF(A5="","",C5*Parâmetros!$B$6*Parâmetros!$B$5) | G5: =IF(A5="","",C5*Parâmetros!$B$7) | H5: =IF(A5="","",E5+F5+G5+D5) | I5: =IF(A5="","",H5*Parâmetros!$B$8) | J5: 12 | K5: =IF(OR(A5="",J5=""),"",J5-H5-J5*Parâmetros!$B$9) | L5: =IF(OR(A5="",J5=""),"",K5/J5) | M5: =IF(A5="","",SUMIFS(Vendas!$C$5:$C$504,Vendas!$B$5:$B$504,A5)) | N5: =IF(A5="","",SUMIFS(Vendas!$J$5:$J$504,Vendas!$B$5:$B$504,A5))
A6: Letreiro de porta (EXEMPLO) | B6: 60 | C6: 4 | D6: 1.5 | E6: =IF(A6="","",B6/1000*Parâmetros!$B$4) | F6: =IF(A6="","",C6*Parâmetros!$B$6*Parâmetros!$B$5) | G6: =IF(A6="","",C6*Parâmetros!$B$7) | H6: =IF(A6="","",E6+F6+G6+D6) | I6: =IF(A6="","",H6*Parâmetros!$B$8) | J6: 35 | K6: =IF(OR(A6="",J6=""),"",J6-H6-J6*Parâmetros!$B$9) | L6: =IF(OR(A6="",J6=""),"",K6/J6) | M6: =IF(A6="","",SUMIFS(Vendas!$C$5:$C$504,Vendas!$B$5:$B$504,A6)) | N6: =IF(A6="","",SUMIFS(Vendas!$J$5:$J$504,Vendas!$B$5:$B$504,A6))
A7: Vaso geométrico (EXEMPLO) | B7: 120 | C7: 6 | D7: 1 | E7: =IF(A7="","",B7/1000*Parâmetros!$B$4) | F7: =IF(A7="","",C7*Parâmetros!$B$6*Parâmetros!$B$5) | G7: =IF(A7="","",C7*Parâmetros!$B$7) | H7: =IF(A7="","",E7+F7+G7+D7) | I7: =IF(A7="","",H7*Parâmetros!$B$8) | J7: 28 | K7: =IF(OR(A7="",J7=""),"",J7-H7-J7*Parâmetros!$B$9) | L7: =IF(OR(A7="",J7=""),"",K7/J7) | M7: =IF(A7="","",SUMIFS(Vendas!$C$5:$C$504,Vendas!$B$5:$B$504,A7)) | N7: =IF(A7="","",SUMIFS(Vendas!$J$5:$J$504,Vendas!$B$5:$B$504,A7))
E8: =IF(A8="","",B8/1000*Parâmetros!$B$4) | F8: =IF(A8="","",C8*Parâmetros!$B$6*Parâmetros!$B$5) | G8: =IF(A8="","",C8*Parâmetros!$B$7) | H8: =IF(A8="","",E8+F8+G8+D8) | I8: =IF(A8="","",H8*Parâmetros!$B$8) | K8: =IF(OR(A8="",J8=""),"",J8-H8-J8*Parâmetros!$B$9) | L8: =IF(OR(A8="",J8=""),"",K8/J8) | M8: =IF(A8="","",SUMIFS(Vendas!$C$5:$C$504,Vendas!$B$5:$B$504,A8)) | N8: =IF(A8="","",SUMIFS(Vendas!$J$5:$J$504,Vendas!$B$5:$B$504,A8))
E9: =IF(A9="","",B9/1000*Parâmetros!$B$4) | F9: =IF(A9="","",C9*Parâmetros!$B$6*Parâmetros!$B$5) | G9: =IF(A9="","",C9*Parâmetros!$B$7) | H9: =IF(A9="","",E9+F9+G9+D9) | I9: =IF(A9="","",H9*Parâmetros!$B$8) | K9: =IF(OR(A9="",J9=""),"",J9-H9-J9*Parâmetros!$B$9) | L9: =IF(OR(A9="",J9=""),"",K9/J9) | M9: =IF(A9="","",SUMIFS(Vendas!$C$5:$C$504,Vendas!$B$5:$B$504,A9)) | N9: =IF(A9="","",SUMIFS(Vendas!$J$5:$J$504,Vendas!$B$5:$B$504,A9))
E10: =IF(A10="","",B10/1000*Parâmetros!$B$4) | F10: =IF(A10="","",C10*Parâmetros!$B$6*Parâmetros!$B$5) | G10: =IF(A10="","",C10*Parâmetros!$B$7) | H10: =IF(A10="","",E10+F10+G10+D10) | I10: =IF(A10="","",H10*Parâmetros!$B$8) | K10: =IF(OR(A10="",J10=""),"",J10-H10-J10*Parâmetros!$B$9) | L10: =IF(OR(A10="",J10=""),"",K10/J10) | M10: =IF(A10="","",SUMIFS(Vendas!$C$5:$C$504,Vendas!$B$5:$B$504,A10)) | N10: =IF(A10="","",SUMIFS(Vendas!$J$5:$J$504,Vendas!$B$5:$B$504,A10))
E11: =IF(A11="","",B11/1000*Parâmetros!$B$4) | F11: =IF(A11="","",C11*Parâmetros!$B$6*Parâmetros!$B$5) | G11: =IF(A11="","",C11*Parâmetros!$B$7) | H11: =IF(A11="","",E11+F11+G11+D11) | I11: =IF(A11="","",H11*Parâmetros!$B$8) | K11: =IF(OR(A11="",J11=""),"",J11-H11-J11*Parâmetros!$B$9) | L11: =IF(OR(A11="",J11=""),"",K11/J11) | M11: =IF(A11="","",SUMIFS(Vendas!$C$5:$C$504,Vendas!$B$5:$B$504,A11)) | N11: =IF(A11="","",SUMIFS(Vendas!$J$5:$J$504,Vendas!$B$5:$B$504,A11))
E12: =IF(A12="","",B12/1000*Parâmetros!$B$4) | F12: =IF(A12="","",C12*Parâmetros!$B$6*Parâmetros!$B$5) | G12: =IF(A12="","",C12*Parâmetros!$B$7) | H12: =IF(A12="","",E12+F12+G12+D12) | I12: =IF(A12="","",H12*Parâmetros!$B$8) | K12: =IF(OR(A12="",J12=""),"",J12-H12-J12*Parâmetros!$B$9) | L12: =IF(OR(A12="",J12=""),"",K12/J12) | M12: =IF(A12="","",SUMIFS(Vendas!$C$5:$C$504,Vendas!$B$5:$B$504,A12)) | N12: =IF(A12="","",SUMIFS(Vendas!$J$5:$J$504,Vendas!$B$5:$B$504,A12))
E13: =IF(A13="","",B13/1000*Parâmetros!$B$4) | F13: =IF(A13="","",C13*Parâmetros!$B$6*Parâmetros!$B$5) | G13: =IF(A13="","",C13*Parâmetros!$B$7) | H13: =IF(A13="","",E13+F13+G13+D13) | I13: =IF(A13="","",H13*Parâmetros!$B$8) | K13: =IF(OR(A13="",J13=""),"",J13-H13-J13*Parâmetros!$B$9) | L13: =IF(OR(A13="",J13=""),"",K13/J13) | M13: =IF(A13="","",SUMIFS(Vendas!$C$5:$C$504,Vendas!$B$5:$B$504,A13)) | N13: =IF(A13="","",SUMIFS(Vendas!$J$5:$J$504,Vendas!$B$5:$B$504,A13))
E14: =IF(A14="","",B14/1000*Parâmetros!$B$4) | F14: =IF(A14="","",C14*Parâmetros!$B$6*Parâmetros!$B$5) | G14: =IF(A14="","",C14*Parâmetros!$B$7) | H14: =IF(A14="","",E14+F14+G14+D14) | I14: =IF(A14="","",H14*Parâmetros!$B$8) | K14: =IF(OR(A14="",J14=""),"",J14-H14-J14*Parâmetros!$B$9) | L14: =IF(OR(A14="",J14=""),"",K14/J14) | M14: =IF(A14="","",SUMIFS(Vendas!$C$5:$C$504,Vendas!$B$5:$B$504,A14)) | N14: =IF(A14="","",SUMIFS(Vendas!$J$5:$J$504,Vendas!$B$5:$B$504,A14))
E15: =IF(A15="","",B15/1000*Parâmetros!$B$4) | F15: =IF(A15="","",C15*Parâmetros!$B$6*Parâmetros!$B$5) | G15: =IF(A15="","",C15*Parâmetros!$B$7) | H15: =IF(A15="","",E15+F15+G15+D15) | I15: =IF(A15="","",H15*Parâmetros!$B$8) | K15: =IF(OR(A15="",J15=""),"",J15-H15-J15*Parâmetros!$B$9) | L15: =IF(OR(A15="",J15=""),"",K15/J15) | M15: =IF(A15="","",SUMIFS(Vendas!$C$5:$C$504,Vendas!$B$5:$B$504,A15)) | N15: =IF(A15="","",SUMIFS(Vendas!$J$5:$J$504,Vendas!$B$5:$B$504,A15))
E16: =IF(A16="","",B16/1000*Parâmetros!$B$4) | F16: =IF(A16="","",C16*Parâmetros!$B$6*Parâmetros!$B$5) | G16: =IF(A16="","",C16*Parâmetros!$B$7) | H16: =IF(A16="","",E16+F16+G16+D16) | I16: =IF(A16="","",H16*Parâmetros!$B$8) | K16: =IF(OR(A16="",J16=""),"",J16-H16-J16*Parâmetros!$B$9) | L16: =IF(OR(A16="",J16=""),"",K16/J16) | M16: =IF(A16="","",SUMIFS(Vendas!$C$5:$C$504,Vendas!$B$5:$B$504,A16)) | N16: =IF(A16="","",SUMIFS(Vendas!$J$5:$J$504,Vendas!$B$5:$B$504,A16))
E17: =IF(A17="","",B17/1000*Parâmetros!$B$4) | F17: =IF(A17="","",C17*Parâmetros!$B$6*Parâmetros!$B$5) | G17: =IF(A17="","",C17*Parâmetros!$B$7) | H17: =IF(A17="","",E17+F17+G17+D17) | I17: =IF(A17="","",H17*Parâmetros!$B$8) | K17: =IF(OR(A17="",J17=""),"",J17-H17-J17*Parâmetros!$B$9) | L17: =IF(OR(A17="",J17=""),"",K17/J17) | M17: =IF(A17="","",SUMIFS(Vendas!$C$5:$C$504,Vendas!$B$5:$B$504,A17)) | N17: =IF(A17="","",SUMIFS(Vendas!$J$5:$J$504,Vendas!$B$5:$B$504,A17))
E18: =IF(A18="","",B18/1000*Parâmetros!$B$4) | F18: =IF(A18="","",C18*Parâmetros!$B$6*Parâmetros!$B$5) | G18: =IF(A18="","",C18*Parâmetros!$B$7) | H18: =IF(A18="","",E18+F18+G18+D18) | I18: =IF(A18="","",H18*Parâmetros!$B$8) | K18: =IF(OR(A18="",J18=""),"",J18-H18-J18*Parâmetros!$B$9) | L18: =IF(OR(A18="",J18=""),"",K18/J18) | M18: =IF(A18="","",SUMIFS(Vendas!$C$5:$C$504,Vendas!$B$5:$B$504,A18)) | N18: =IF(A18="","",SUMIFS(Vendas!$J$5:$J$504,Vendas!$B$5:$B$504,A18))
E19: =IF(A19="","",B19/1000*Parâmetros!$B$4) | F19: =IF(A19="","",C19*Parâmetros!$B$6*Parâmetros!$B$5) | G19: =IF(A19="","",C19*Parâmetros!$B$7) | H19: =IF(A19="","",E19+F19+G19+D19) | I19: =IF(A19="","",H19*Parâmetros!$B$8) | K19: =IF(OR(A19="",J19=""),"",J19-H19-J19*Parâmetros!$B$9) | L19: =IF(OR(A19="",J19=""),"",K19/J19) | M19: =IF(A19="","",SUMIFS(Vendas!$C$5:$C$504,Vendas!$B$5:$B$504,A19)) | N19: =IF(A19="","",SUMIFS(Vendas!$J$5:$J$504,Vendas!$B$5:$B$504,A19))
... E54: =IF(A54="","",B54/1000*Parâmetros!$B$4) | F54: =IF(A54="","",C54*Parâmetros!$B$6*Parâmetros!$B$5) | G54: =IF(A54="","",C54*Parâmetros!$B$7) | H54: =IF(A54="","",E54+F54+G54+D54) | I54: =IF(A54="","",H54*Parâmetros!$B$8) | K54: =IF(OR(A54="",J54=""),"",J54-H54-J54*Parâmetros!$B$9) | L54: =IF(OR(A54="",J54=""),"",K54/J54) | M54: =IF(A54="","",SUMIFS(Vendas!$C$5:$C$504,Vendas!$B$5:$B$504,A54)) | N54: =IF(A54="","",SUMIFS(Vendas!$J$5:$J$504,Vendas!$B$5:$B$504,A54))

Sheet Vendas
A1: Vendas
A2: Uma linha por venda. Preencha só as colunas amarelas.
A4: Data | B4: Produto | C4: Qtd | D4: Preço unitário cobrado | E4: Canal | F4: Taxa do canal (%) | G4: Receita | H4: Taxa (R$) | I4: Custo de produção | J4: LUCRO
A5: 46303 | B5: Chaveiro com nome (EXEMPLO) | C5: 10 | D5: 12 | E5: WhatsApp | F5: 0 | G5: =IF(B5="","",C5*D5) | H5: =IF(B5="","",G5*F5) | I5: =IF(B5="","",C5*IFERROR(INDEX(Produtos!$H$5:$H$54,MATCH(B5,Produtos!$A$5:$A$54,0)),0)) | J5: =IF(B5="","",G5-H5-I5)
A6: 46304 | B6: Letreiro de porta (EXEMPLO) | C6: 1 | D6: 35 | E6: Mercado Livre | F6: 0.15 | G6: =IF(B6="","",C6*D6) | H6: =IF(B6="","",G6*F6) | I6: =IF(B6="","",C6*IFERROR(INDEX(Produtos!$H$5:$H$54,MATCH(B6,Produtos!$A$5:$A$54,0)),0)) | J6: =IF(B6="","",G6-H6-I6)
A7: 46305 | B7: Vaso geométrico (EXEMPLO) | C7: 2 | D7: 28 | E7: Shopee | F7: 0.15 | G7: =IF(B7="","",C7*D7) | H7: =IF(B7="","",G7*F7) | I7: =IF(B7="","",C7*IFERROR(INDEX(Produtos!$H$5:$H$54,MATCH(B7,Produtos!$A$5:$A$54,0)),0)) | J7: =IF(B7="","",G7-H7-I7)
G8: =IF(B8="","",C8*D8) | H8: =IF(B8="","",G8*F8) | I8: =IF(B8="","",C8*IFERROR(INDEX(Produtos!$H$5:$H$54,MATCH(B8,Produtos!$A$5:$A$54,0)),0)) | J8: =IF(B8="","",G8-H8-I8)
G9: =IF(B9="","",C9*D9) | H9: =IF(B9="","",G9*F9) | I9: =IF(B9="","",C9*IFERROR(INDEX(Produtos!$H$5:$H$54,MATCH(B9,Produtos!$A$5:$A$54,0)),0)) | J9: =IF(B9="","",G9-H9-I9)
G10: =IF(B10="","",C10*D10) | H10: =IF(B10="","",G10*F10) | I10: =IF(B10="","",C10*IFERROR(INDEX(Produtos!$H$5:$H$54,MATCH(B10,Produtos!$A$5:$A$54,0)),0)) | J10: =IF(B10="","",G10-H10-I10)
G11: =IF(B11="","",C11*D11) | H11: =IF(B11="","",G11*F11) | I11: =IF(B11="","",C11*IFERROR(INDEX(Produtos!$H$5:$H$54,MATCH(B11,Produtos!$A$5:$A$54,0)),0)) | J11: =IF(B11="","",G11-H11-I11)
G12: =IF(B12="","",C12*D12) | H12: =IF(B12="","",G12*F12) | I12: =IF(B12="","",C12*IFERROR(INDEX(Produtos!$H$5:$H$54,MATCH(B12,Produtos!$A$5:$A$54,0)),0)) | J12: =IF(B12="","",G12-H12-I12)
G13: =IF(B13="","",C13*D13) | H13: =IF(B13="","",G13*F13) | I13: =IF(B13="","",C13*IFERROR(INDEX(Produtos!$H$5:$H$54,MATCH(B13,Produtos!$A$5:$A$54,0)),0)) | J13: =IF(B13="","",G13-H13-I13)
G14: =IF(B14="","",C14*D14) | H14: =IF(B14="","",G14*F14) | I14: =IF(B14="","",C14*IFERROR(INDEX(Produtos!$H$5:$H$54,MATCH(B14,Produtos!$A$5:$A$54,0)),0)) | J14: =IF(B14="","",G14-H14-I14)
G15: =IF(B15="","",C15*D15) | H15: =IF(B15="","",G15*F15) | I15: =IF(B15="","",C15*IFERROR(INDEX(Produtos!$H$5:$H$54,MATCH(B15,Produtos!$A$5:$A$54,0)),0)) | J15: =IF(B15="","",G15-H15-I15)
G16: =IF(B16="","",C16*D16) | H16: =IF(B16="","",G16*F16) | I16: =IF(B16="","",C16*IFERROR(INDEX(Produtos!$H$5:$H$54,MATCH(B16,Produtos!$A$5:$A$54,0)),0)) | J16: =IF(B16="","",G16-H16-I16)
G17: =IF(B17="","",C17*D17) | H17: =IF(B17="","",G17*F17) | I17: =IF(B17="","",C17*IFERROR(INDEX(Produtos!$H$5:$H$54,MATCH(B17,Produtos!$A$5:$A$54,0)),0)) | J17: =IF(B17="","",G17-H17-I17)
G18: =IF(B18="","",C18*D18) | H18: =IF(B18="","",G18*F18) | I18: =IF(B18="","",C18*IFERROR(INDEX(Produtos!$H$5:$H$54,MATCH(B18,Produtos!$A$5:$A$54,0)),0)) | J18: =IF(B18="","",G18-H18-I18)
G19: =IF(B19="","",C19*D19) | H19: =IF(B19="","",G19*F19) | I19: =IF(B19="","",C19*IFERROR(INDEX(Produtos!$H$5:$H$54,MATCH(B19,Produtos!$A$5:$A$54,0)),0)) | J19: =IF(B19="","",G19-H19-I19)
... G504: =IF(B504="","",C504*D504) | H504: =IF(B504="","",G504*F504) | I504: =IF(B504="","",C504*IFERROR(INDEX(Produtos!$H$5:$H$54,MATCH(B504,Produtos!$A$5:$A$54,0)),0)) | J504: =IF(B504="","",G504-H504-I504)

Sheet Gastos
A1: Gastos
A2: Tudo que você comprou para o negócio, inclusive a impressora.
A4: Data | B4: Descrição | C4: Categoria | D4: Valor (R$)
A5: 46296 | B5: Impressora Bambu A1 (EXEMPLO, troque pelo valor real) | C5: Impressora e peças | D5: 3500
A6: 46300 | B6: 5 rolos de PLA (EXEMPLO) | C6: Filamento | D6: 500
